jin2for/__init__.py
jin2for/intrinsic_type.py
jin2for/kind_info.py
jin2for/data/kinds.f90
jin2for-0.1.0.dist-info/LICENSE
jin2for-0.1.0.dist-info/METADATA
jin2for-0.1.0.dist-info/WHEEL
jin2for-0.1.0.dist-info/entry_points.txt
jin2for-0.1.0.dist-info/top_level.txt
jin2for-0.1.0.dist-info/RECORD
