Metadata-Version: 2.1
Name: jin2for
Version: 0.1.0
Summary: A jinja2-based template engine for FORTRAN projects
Home-page: https://gitlab.com/fverdugo/jin2for
Author: Francesc Verdugo
Author-email: fverdugo@cimne.upc.edu
License: UNKNOWN
Platform: UNKNOWN
Classifier: Programming Language :: Python :: 3.7
Classifier: Programming Language :: Python :: 3.6
Classifier: Programming Language :: Python :: 3.5
Classifier: Programming Language :: Fortran
Classifier: Operating System :: POSIX :: Linux
Classifier: License :: OSI Approved :: GNU General Public License v3 (GPLv3)
Classifier: Operating System :: MacOS
Requires-Dist: argparse
Requires-Dist: jinja2
